{
    "000000351530.jpg": "Describe this image in detail.",
    "000000511760.jpg": "Describe this image in detail.",
    "000000038825.jpg": "Describe this image in detail.",
    "000000097924.jpg": "Describe this image in detail.",
    "000000356531.jpg": "Describe this image in detail.",
    "000000295231.jpg": "Describe this image in detail.",
    "000000176799.jpg": "Describe this image in detail.",
    "000000342397.jpg": "Describe this image in detail.",
    "000000286422.jpg": "Describe this image in detail.",
    "000000524742.jpg": "Describe this image in detail."
} 